{
  "name": "Adafruit Qualia ESP32-S3 RGB666",
  "connections": {
    "serial": {
      "availablePorts": [
        "Serial"
      ],
      "defaultPort": "Serial",
      "defaultBaud": 115200,
      "supportedBauds": [
        9600,
        19200,
        38400,
        57600,
        115200,
        230400,
        460800,
        921600
      ]
    },
    "ble": {},
    "tcp": {},
    "http": {}
  },
  "pwm": {
    "min": 0,
    "max": 255,
    "method": "analogWrite"
  },
  "dac": {},
  "adc": {
    "bits": 12,
    "max": 4095,
    "defaultRefVolts": "3.3"
  },
  "pins": [
    {
      "name": "PCA_TFT_SCK",
      "label": "PCA_TFT_SCK (GPIO0)",
      "codeName": "PCA_TFT_SCK",
      "capabilities": [
        "digital_input",
        "digital_output",
        "pwm_output"
      ],
      "notes": "Must be HIGH for normal boot"
    },
    {
      "name": "PCA_TFT_CS",
      "label": "PCA_TFT_CS (GPIO1)",
      "codeName": "PCA_TFT_CS",
      "capabilities": [
        "analog_input",
        "digital_input",
        "digital_output",
        "pwm_output"
      ]
    },
    {
      "name": "PCA_TFT_RESET",
      "label": "PCA_TFT_RESET (GPIO2)",
      "codeName": "PCA_TFT_RESET",
      "capabilities": [
        "analog_input",
        "digital_input",
        "digital_output",
        "pwm_output"
      ]
    },
    {
      "name": "PCA_CPT_IRQ",
      "label": "PCA_CPT_IRQ (GPIO3)",
      "codeName": "PCA_CPT_IRQ",
      "capabilities": [
        "analog_input",
        "digital_input",
        "digital_output",
        "pwm_output"
      ],
      "notes": "Must be LOW or floating on reboot"
    },
    {
      "name": "PCA_TFT_BACKLIGHT",
      "label": "PCA_TFT_BACKLIGHT (GPIO4)",
      "codeName": "PCA_TFT_BACKLIGHT",
      "capabilities": [
        "analog_input",
        "digital_input",
        "digital_output",
        "pwm_output"
      ]
    },
    {
      "name": "SCK",
      "label": "SCK (GPIO5)",
      "codeName": "SCK",
      "capabilities": [
        "analog_input",
        "digital_input",
        "digital_output",
        "pwm_output",
        "spi_sck"
      ]
    },
    {
      "name": "MISO",
      "label": "MISO (GPIO6)",
      "codeName": "MISO",
      "capabilities": [
        "analog_input",
        "digital_input",
        "digital_output",
        "pwm_output",
        "spi_miso"
      ]
    },
    {
      "name": "MOSI",
      "label": "MOSI (GPIO7)",
      "codeName": "MOSI",
      "capabilities": [
        "analog_input",
        "digital_input",
        "digital_output",
        "pwm_output",
        "spi_mosi"
      ]
    },
    {
      "name": "SDA",
      "label": "SDA (GPIO8)",
      "codeName": "SDA",
      "capabilities": [
        "analog_input",
        "digital_input",
        "digital_output",
        "pwm_output",
        "i2c_sda"
      ]
    },
    {
      "name": "TFT_R3",
      "label": "TFT_R3 (GPIO9)",
      "codeName": "TFT_R3",
      "capabilities": [
        "analog_input",
        "digital_input",
        "digital_output",
        "pwm_output"
      ]
    },
    {
      "name": "TFT_R2",
      "label": "TFT_R2 (GPIO10)",
      "codeName": "TFT_R2",
      "capabilities": [
        "analog_input",
        "digital_input",
        "digital_output",
        "pwm_output"
      ]
    },
    {
      "name": "TFT_R1",
      "label": "TFT_R1 (GPIO11)",
      "codeName": "TFT_R1",
      "capabilities": [
        "analog_input",
        "digital_input",
        "digital_output",
        "pwm_output"
      ]
    },
    {
      "name": "TFT_G5",
      "label": "TFT_G5 (GPIO12)",
      "codeName": "TFT_G5",
      "capabilities": [
        "analog_input",
        "digital_input",
        "digital_output",
        "pwm_output"
      ]
    },
    {
      "name": "TFT_G4",
      "label": "TFT_G4 (GPIO13)",
      "codeName": "TFT_G4",
      "capabilities": [
        "analog_input",
        "digital_input",
        "digital_output",
        "pwm_output"
      ]
    },
    {
      "name": "TFT_G3",
      "label": "TFT_G3 (GPIO14)",
      "codeName": "TFT_G3",
      "capabilities": [
        "analog_input",
        "digital_input",
        "digital_output",
        "pwm_output"
      ]
    },
    {
      "name": "SS",
      "label": "SS (GPIO15)",
      "codeName": "SS",
      "capabilities": [
        "analog_input",
        "digital_input",
        "digital_output",
        "pwm_output",
        "spi_ss"
      ]
    },
    {
      "name": "A1",
      "label": "A1 (GPIO16)",
      "codeName": "A1",
      "capabilities": [
        "serial_tx"
      ]
    },
    {
      "name": "A0",
      "label": "A0 (GPIO17)",
      "codeName": "A0",
      "capabilities": [
        "serial_rx"
      ]
    },
    {
      "name": "SCL",
      "label": "SCL (GPIO18)",
      "codeName": "SCL",
      "capabilities": [
        "analog_input",
        "digital_input",
        "digital_output",
        "pwm_output",
        "i2c_scl"
      ]
    },
    {
      "name": "TFT_G2",
      "label": "TFT_G2 (GPIO21)",
      "codeName": "TFT_G2",
      "capabilities": [
        "digital_input",
        "digital_output",
        "pwm_output"
      ]
    },
    {
      "name": "TFT_B3",
      "label": "TFT_B3 (GPIO38)",
      "codeName": "TFT_B3",
      "capabilities": [
        "digital_input",
        "digital_output",
        "pwm_output"
      ]
    },
    {
      "name": "TFT_B2",
      "label": "TFT_B2 (GPIO39)",
      "codeName": "TFT_B2",
      "capabilities": [
        "digital_input",
        "digital_output",
        "pwm_output"
      ]
    },
    {
      "name": "TFT_B1",
      "label": "TFT_B1 (GPIO40)",
      "codeName": "TFT_B1",
      "capabilities": [
        "digital_input",
        "digital_output",
        "pwm_output"
      ]
    },
    {
      "name": "TFT_HSYNC",
      "label": "TFT_HSYNC (GPIO41)",
      "codeName": "TFT_HSYNC",
      "capabilities": [
        "digital_input",
        "digital_output",
        "pwm_output"
      ]
    },
    {
      "name": "TFT_VSYNC",
      "label": "TFT_VSYNC (GPIO42)",
      "codeName": "TFT_VSYNC",
      "capabilities": [
        "digital_input",
        "digital_output",
        "pwm_output"
      ]
    },
    {
      "name": "GPIO43",
      "label": "GPIO43",
      "codeName": "43",
      "capabilities": [
        "digital_input",
        "digital_output",
        "pwm_output"
      ],
      "notes": "Check if available on board"
    },
    {
      "name": "GPIO44",
      "label": "GPIO44",
      "codeName": "44",
      "capabilities": [
        "digital_input",
        "digital_output",
        "pwm_output"
      ],
      "notes": "Check if available on board"
    },
    {
      "name": "TFT_B5",
      "label": "TFT_B5 (GPIO45)",
      "codeName": "TFT_B5",
      "capabilities": [
        "digital_input",
        "digital_output",
        "pwm_output"
      ],
      "notes": "Must be LOW or floating on reboot"
    },
    {
      "name": "TFT_R4",
      "label": "TFT_R4 (GPIO46)",
      "codeName": "TFT_R4",
      "capabilities": [
        "digital_input",
        "digital_output",
        "pwm_output"
      ],
      "notes": "Must be LOW or floating on reboot"
    },
    {
      "name": "TFT_G1",
      "label": "TFT_G1 (GPIO47)",
      "codeName": "TFT_G1",
      "capabilities": [
        "digital_input",
        "digital_output",
        "pwm_output"
      ]
    },
    {
      "name": "TFT_G0",
      "label": "TFT_G0 (GPIO48)",
      "codeName": "TFT_G0",
      "capabilities": [
        "digital_input",
        "digital_output",
        "pwm_output"
      ]
    }
  ],
  "family": "esp32",
  "chip": "esp32s3",
  "familyDisplayName": "ESP32",
  "familySortOrder": 100
}
